XRP_CONVERTER/__init__.py
XRP_CONVERTER/xrp_w_convert.py
XRP_CONVERTER-0.2.0.dist-info/METADATA
XRP_CONVERTER-0.2.0.dist-info/WHEEL
XRP_CONVERTER-0.2.0.dist-info/entry_points.txt
XRP_CONVERTER-0.2.0.dist-info/top_level.txt
XRP_CONVERTER-0.2.0.dist-info/RECORD
