Metadata-Version: 2.2
Name: XRP_CONVERTER
Version: 0.2.0
Summary: A cool XRP conversion library with extra tools.
Author: kakz
Requires-Python: >=3.8
Requires-Dist: requests
Requires-Dist: pandas
Requires-Dist: numpy
Requires-Dist: tqdm
Requires-Dist: matplotlib
Requires-Dist: scikit-learn
Requires-Dist: flask
Requires-Dist: beautifulsoup4
Requires-Dist: pytest
Requires-Dist: pydantic
Requires-Dist: asyncio
Dynamic: author
Dynamic: description
Dynamic: description-content-type
Dynamic: requires-dist
Dynamic: requires-python
Dynamic: summary
